requirements.txt
setup.py
gists_id/__init__.py
gists_id/__main__.py
gists_id.egg-info/PKG-INFO
gists_id.egg-info/SOURCES.txt
gists_id.egg-info/dependency_links.txt
gists_id.egg-info/requires.txt
gists_id.egg-info/top_level.txt