Metadata-Version: 2.1
Name: gists-id
Version: 2020.7.1
Summary: get gists id
Home-page: https://github.com/andrewp-as-is/gists_id.py
License: Unlicense
Keywords: gists id
Platform: UNKNOWN
Classifier: License :: Public Domain
Classifier: Operating System :: OS Independent
Classifier: Programming Language :: Python :: 3
